topsis/__init__.py
topsis/__main__.py
Topsis_Lovely_102218034-1.0.1.dist-info/LICENSE
Topsis_Lovely_102218034-1.0.1.dist-info/METADATA
Topsis_Lovely_102218034-1.0.1.dist-info/WHEEL
Topsis_Lovely_102218034-1.0.1.dist-info/entry_points.txt
Topsis_Lovely_102218034-1.0.1.dist-info/top_level.txt
Topsis_Lovely_102218034-1.0.1.dist-info/RECORD
